{"cameraMode":{"drawMode":0,"name":"Shaded","section":"Shading Mode"},"sceneLighting":true,"audioPlay":false,"sceneViewState":{"m_AlwaysRefresh":false,"showFog":true,"showSkybox":true,"showFlares":true,"showImageEffects":true,"showParticleSystems":true,"showVisualEffectGraphs":true,"m_FxEnabled":true},"in2DMode":false,"pivot":{"x":-0.04532623291015625,"y":-2.7178704738616945,"z":4.719717502593994},"rotation":{"x":-0.14700239896774293,"y":0.842129111289978,"z":-0.28592216968536379,"w":-0.43297624588012698},"size":1.2739068269729615,"orthographic":false}